{
  "company": {
    "name": "有限会社トキワ工業",
    "nameShort": "トキワ工業",
    "nameEn": "TOKIWA",
    "id": "tokiwa",
    "ceo": "鴇澤 進一",
    "established": "",
    "capital": "",
    "revenue": "",
    "employees": "",
    "business": "製造業（制御盤・配電盤・分電盤・機械カバー・ブラケット・ステンレス加工・鋼材加工・塗装・組付け・軽微品加工）",
    "license": "",
    "catchphrase": "",
    "mission": ""
  },
  "contact": {
    "phone": "0567-33-1330",
    "phoneFormatted": "0567-33-1330",
    "phoneTel": "0567331330",
    "fax": "0567-33-1320",
    "email": "",
    "hours": "8:30〜17:30",
    "recruitContact": ""
  },
  "locations": {
    "headquarters": {
      "name": "本社",
      "zipCode": "496-0016",
      "address": "愛知県津島市白浜町八丁目59-1",
      "access": "JR蟹江駅 車で10分以内",
      "mapUrl": ""
    },
    "branches": []
  },
  "social": {
    "instagram": ""
  },
  "images": {
    "logo": "/images/logo.png",
    "logoSquare": "/images/logo-square.png",
    "logoOnly": "/images/logo-only.png"
  },
  "seo": {
    "siteUrl": "https://tokiwa-kogyo.co.jp",
    "titleSuffix": " | 有限会社トキワ工業",
    "defaultTitle": "有限会社トキワ工業 | 制御盤・配電盤・機械カバー製造",
    "defaultDescription": "愛知県津島市のトキワ工業。制御盤・配電盤・分電盤・機械カバー・ブラケットの製造。10分の1単位の精密加工技術で、お客様の製品価値を高めます。"
  },
  "stats": {
    "yearsInBusiness": "",
    "projectsCompleted": "",
    "employees": "",
    "retentionRate": ""
  },
  "history": [],
  "services": [],
  "works": [],
  "news": [],
  "recruit": {
    "catchphrase": "",
    "subCatchphrase": "",
    "data": [],
    "benefits": {
      "vacation": [],
      "allowances": [],
      "facilities": []
    },
    "positions": {
      "highSchool": { "title": "", "items": [] },
      "midCareer": { "title": "", "items": [] }
    },
    "faq": [],
    "interviews": []
  },
  "ceo": {
    "name": "鴇澤 進一",
    "title": "代表取締役",
    "image": "",
    "message": []
  }
}
